src/__init__.py
src/safelogger.py
src/structlog_support.py
src/filters/__init__.py
src/filters/redact.py
src/handlers/__init__.py
src/handlers/cloud.py
src/utils/__init__.py
src/utils/config.py
py_safelogger-0.3.0.dist-info/METADATA
py_safelogger-0.3.0.dist-info/WHEEL
py_safelogger-0.3.0.dist-info/top_level.txt
py_safelogger-0.3.0.dist-info/RECORD
