Metadata-Version: 2.1
Name: py_safelogger
Version: 0.3.0
Summary: Biblioteca de logging estruturado para Python
Author: Bruno Schuster Fraga
Author-email: Bruno Schuster Fraga <brunofraga_@outlook.com.br>
License: MIT
Requires-Python: >=3.8
Requires-Dist: python-json-logger
Requires-Dist: structlog
Provides-Extra: test
Requires-Dist: pytest>=8.0.0; extra == "test"
Requires-Dist: pytest-cov>=5.0.0; extra == "test"
Requires-Dist: PyYAML>=6.0; extra == "test"
Provides-Extra: yaml
Requires-Dist: PyYAML>=6.0; extra == "yaml"
